[
    {"intent": "greeting", "text": "hi"},
    {"intent": "greeting", "text": "hello"},
    {"intent": "greeting", "text": "hey there"},
    {"intent": "greeting", "text": "good morning"},
    {"intent": "greeting", "text": "yo!"},
    
    {"intent": "ask_age", "text": "how old are you?"},
    {"intent": "ask_age", "text": "what's your age?"},
    {"intent": "ask_age", "text": "can I know your age?"},
    
    {"intent": "ask_time", "text": "what time is it?"},
    {"intent": "ask_time", "text": "do you know the current time?"},
    {"intent": "ask_time", "text": "tell me the time now."},
  
    {"intent": "ask_weather", "text": "what is the weather like today?"},
    {"intent": "ask_weather", "text": "can you check the weather?"},
    {"intent": "ask_weather", "text": "is it raining right now?"},
    {"intent": "ask_weather", "text": "do I need an umbrella today?"},
    {"intent": "ask_weather", "text": "how’s the weather?"},
    {"intent": "ask_weather", "text": "tell me the current forecast"},
    {"intent": "ask_weather", "text": "will it be sunny today?"},
    {"intent": "ask_weather", "text": "can you tell me if it's cold outside?"},
    {"intent": "ask_weather", "text": "what's the weather in Paris"},
    {"intent": "ask_weather", "text": "do I need a jacket in San Francisco"},

    
    {"intent": "ask_news", "text": "show me tech news"},
    {"intent": "ask_news", "text": "what's going on in the stock market"},
    {"intent": "ask_news", "text": "give me the latest headlines"},
    {"intent": "ask_news", "text": "what's happening in tech"},
    {"intent": "ask_news", "text": "any updates from the stock market?"},
    {"intent": "ask_news", "text": "give me financial news"},
    {"intent": "ask_news", "text": "latest from the business world"},
    {"intent": "ask_news", "text": "any tech news today?"},


    {"intent": "ask_name", "text": "what's your name?"},
    {"intent": "ask_name", "text": "do you have a name?"},
    {"intent": "ask_name", "text": "can you tell me your name?"},
    {"intent": "ask_name", "text": "what is your name?"},

    {"intent": "ask_search", "text": "who is albert einstein"},
    {"intent": "ask_search", "text": "what is machine learning"},
    {"intent": "ask_search", "text": "tell me about mars"},
    {"intent": "ask_search", "text": "who is isaac newton"},
    {"intent": "ask_search", "text": "who is elon musk"},
    {"intent": "ask_search", "text": "what is the sun made of"},
    {"intent": "ask_search", "text": "tell me about black holes"},
    {"intent": "ask_search", "text": "explain photosynthesis"},
    {"intent": "ask_search", "text": "define quantum mechanics"},
    {"intent": "ask_search", "text": "give me information on AI"},
    {"intent": "ask_search", "text": "what do you know about spacex"},
    {"intent": "ask_search", "text": "what is general relativity"},
    {"intent": "ask_search", "text": "tell me about World War II"},
    {"intent": "ask_search", "text": "how do volcanoes erupt"},
    {"intent": "ask_search", "text": "what causes earthquakes"},
    {"intent": "ask_search", "text": "who discovered gravity"},

    {"intent": "ask_math", "text": "what is 12 x 12"},
    {"intent": "ask_math", "text": "calculate 100 divided by 5"},
    {"intent": "ask_math", "text": "what is 7 + 3"},
    {"intent": "ask_math", "text": "13*9"},
    {"intent": "ask_math", "text": "what is 12 * (3 + 4)?"},
    {"intent": "ask_math", "text": "calculate 100 / (2 + 3)"},
    {"intent": "ask_math", "text": "solve 2 ** 5"},
    {"intent": "ask_math", "text": "13 x (2 + 1)"},
    {"intent": "ask_math", "text": "compute 7 * 8"},
    {"intent": "ask_math", "text": "what is 5 plus 9 times 2"},
    {"intent": "ask_math", "text": "tell me 9 + 9"},
    {"intent": "ask_math", "text": "what's 3 squared"},
    {"intent": "ask_math", "text": "what's 3 to the power of 4"},
    {"intent": "ask_math", "text": "evaluate 10 + 3 * (2 + 1)"},
    {"intent": "ask_math", "text": "solve 8 + 6"},
    {"intent": "ask_math", "text": "compute 45 - 12"},
    {"intent": "ask_math", "text": "100 * 1.5"},
    {"intent": "ask_math", "text": "evaluate 2**10"},
    {"intent": "ask_math", "text": "12 * (3 + 4)"},
    {"intent": "ask_math", "text": "what’s 2.5 squared"},
    {"intent": "ask_math", "text": "solve (5 + 3) * 4"},
    {"intent": "ask_math", "text": "can you calculate 15 divided by 3?"},
    {"intent": "ask_math", "text": "how much is 22% of 50"},
    {"intent": "ask_math", "text": "what’s the square root of 64?"},

    {"intent": "add_todo", "text": "remind me to walk the dog"},
    {"intent": "add_todo", "text": "add 'call mom' to my to-do list"},
    {"intent": "add_todo", "text": "remember to take out the trash"},
    {"intent": "add_todo", "text": "please remember to check my emails"},
    {"intent": "add_todo", "text": "add 'finish cs project' to the list"},
    {"intent": "add_todo", "text": "note to call the dentist"},
    {"intent": "add_todo", "text": "remind me to finish my math homework"},
    {"intent": "add_todo", "text": "remember to call mom at 5"},
    {"intent": "add_todo", "text": "add 'buy groceries' to my list"},
    {"intent": "add_todo", "text": "save 'submit application' in my reminders"},
    {"intent": "add_todo", "text": "note down complete CS project"},
    {"intent": "add_todo", "text": "i need to wash the car"},
    {"intent": "add_todo", "text": "set a reminder for dentist appointment"},
    {"intent": "add_todo", "text": "put 'finish essay' on my to-do list"},
    {"intent": "add_todo", "text": "track 'renew license' task"},
    {"intent": "add_todo", "text": "keep 'meet advisor' in mind"},


    {"intent": "get_todo", "text": "what's on my to-do list"},
    {"intent": "get_todo", "text": "what is on my to-do list"},
    {"intent": "get_todo", "text": "show me my to-do list"},
    {"intent": "get_todo", "text": "show me my reminders"},
    {"intent": "get_todo", "text": "what tasks do I have?"},
    {"intent": "get_todo", "text": "can you read my to-do list?"},
    
    {"intent": "clear_todo", "text": "clear my reminders"},
    {"intent": "clear_todo", "text": "delete all to-dos"},
    {"intent": "clear_todo", "text": "clear my to-do list"},
    {"intent": "clear_todo", "text": "clear out all my tasks"},
    {"intent": "clear_todo", "text": "remove everything from my to-do list"},


    {"intent": "goodbye", "text": "bye"},
    {"intent": "goodbye", "text": "see you later"},
    {"intent": "goodbye", "text": "I'm leaving now"},
    {"intent": "goodbye", "text": "talk to you later"}
  ]
  